mortal/__init__.py
mortal/build/__init__.py
mortal/build/build_main.pyd
mortal/build/text.pyd
mortal/crypt/__init__.py
mortal/crypt/crypt_main.pyd
mortal/curl/__init__.py
mortal/curl/curl_main.pyd
mortal/curl/extract.pyd
mortal/curl/parse.pyd
mortal/curl/text.pyd
mortal/database/__init__.py
mortal/database/execute_main.pyd
mortal/database/orm_main.pyd
mortal/database/common/__init__.py
mortal/database/common/cleanse_params.pyd
mortal/database/common/connect.pyd
mortal/database/common/orm_column_map.pyd
mortal/database/common/orm_create_map.pyd
mortal/database/common/orm_exists_map.pyd
mortal/database/common/orm_operation.pyd
mortal/database/common/read_tables_columns.pyd
mortal/database/common/sql_params_map.pyd
mortal/database/common/sql_url_map.pyd
mortal/database/domian/__init__.py
mortal/database/domian/hive.pyd
mortal/database/domian/impala.pyd
mortal/database/domian/mysql.pyd
mortal/database/domian/oracle.pyd
mortal/database/domian/postgresql.pyd
mortal/database/domian/sqlite.pyd
mortal/database/domian/sqlserver.pyd
mortal/database/domian/starrocks.pyd
mortal/database/hive/__init__.py
mortal/database/hive/hive_params_dict.pyd
mortal/database/hive/hive_url.pyd
mortal/database/impala/__init__.py
mortal/database/impala/impala_params_dict.pyd
mortal/database/impala/impala_url.pyd
mortal/database/mysql/__init__.py
mortal/database/mysql/mysql_orm_columns.pyd
mortal/database/mysql/mysql_orm_map.pyd
mortal/database/mysql/mysql_params_dict.pyd
mortal/database/mysql/mysql_url.pyd
mortal/database/oracle/__init__.py
mortal/database/oracle/oracle_params_dict.pyd
mortal/database/oracle/oracle_url.pyd
mortal/database/postgresql/__init__.py
mortal/database/postgresql/postgresql_params_dict.pyd
mortal/database/postgresql/postgresql_url.pyd
mortal/database/sqlite/__init__.py
mortal/database/sqlite/sqlite_orm_columns.pyd
mortal/database/sqlite/sqlite_orm_create_table.pyd
mortal/database/sqlite/sqlite_orm_map.pyd
mortal/database/sqlite/sqlite_params_dict.pyd
mortal-1.13.1.dist-info/METADATA
mortal-1.13.1.dist-info/WHEEL
mortal-1.13.1.dist-info/top_level.txt
mortal-1.13.1.dist-info/RECORD
